[{"name":"Alfonso","code":"0402101000","type":"Mun","zip_code":"4122","district":"4th"},{"name":"Amadeo","code":"0402102000","type":"Mun","zip_code":"4122","district":"4th"},{"name":"City of Bacoor","code":"0402103000","type":"City","zip_code":"4102","district":"2nd"},{"name":"Carmona","code":"0402104000","type":"Mun","zip_code":"4107","district":"1st"},{"name":"City of Cavite","code":"0402105000","type":"City","zip_code":"4100","district":"1st"},{"name":"City of Dasmari\u00c3\u00b1as","code":"0402106000","type":"City","zip_code":"4114","district":"4th"},{"name":"General Emilio Aguinaldo","code":"0402107000","type":"Mun","zip_code":"4111","district":"4th"},{"name":"City of General Trias","code":"0402108000","type":"City","zip_code":"4107","district":"6th"},{"name":"City of Imus","code":"0402109000","type":"City","zip_code":"4103","district":"1st"},{"name":"Indang","code":"0402110000","type":"Mun","zip_code":"4122","district":"Lone"},{"name":"Kawit","code":"0402111000","type":"Mun","zip_code":"4104","district":"1st"},{"name":"Magallanes","code":"0402112000","type":"Mun","zip_code":"","district":"4th"},{"name":"Maragondon","code":"0402113000","type":"Mun","zip_code":"4112","district":"4th"},{"name":"Mendez","code":"0402114000","type":"Mun","zip_code":"","district":"4th"},{"name":"Naic","code":"0402115000","type":"Mun","zip_code":"4105","district":"2nd"},{"name":"Noveleta","code":"0402116000","type":"Mun","zip_code":"4106","district":"1st"},{"name":"Rosario","code":"0402117000","type":"Mun","zip_code":"4106","district":"1st"},{"name":"Silang","code":"0402118000","type":"Mun","zip_code":"4118","district":"4th"},{"name":"City of Tagaytay","code":"0402119000","type":"City","zip_code":"4120","district":"6th"},{"name":"Tanza","code":"0402120000","type":"Mun","zip_code":"4108","district":"6th"},{"name":"Ternate","code":"0402121000","type":"Mun","zip_code":"4117","district":"2nd"},{"name":"City of Trece Martires ","code":"0402122000","type":"City","zip_code":"4107","district":"6th"},{"name":"Gen. Mariano Alvarez","code":"0402123000","type":"Mun","zip_code":"4117","district":"4th"}]